LICENSE
README.md
setup.py
pythonworley/__init__.py
pythonworley/worley.py
pythonworley.egg-info/PKG-INFO
pythonworley.egg-info/SOURCES.txt
pythonworley.egg-info/dependency_links.txt
pythonworley.egg-info/requires.txt
pythonworley.egg-info/top_level.txt