Metadata-Version: 2.1
Name: pythonworley
Version: 0.0.1
Summary: Worley noise in python - seamlessly tile in any dimensions
Home-page: https://github.com/timpyrkov/pythonworley
Author: Tim Pyrkov
Author-email: tim.pyrkov@gmail.com
License: MIT License
Platform: UNKNOWN
Classifier: Programming Language :: Python :: 3
Classifier: License :: OSI Approved :: MIT License
Classifier: Topic :: Artistic Software
Requires-Python: >=3.6
License-File: LICENSE
